AUTHORS
CONTRIBUTING
ChangeLog.txt
MANIFEST.in
README.rst
ez_setup.py
opbasm.py
pb_update.py
setup.cfg
setup.py
doc/Makefile
doc/conf.py
doc/index.rst
doc/make.bat
doc/_static/project.css
doc/_static/tty/demo.ttyrec
doc/_static/tty/term.min.js
doc/_static/tty/tty-player.min.css
doc/_static/tty/tty-player.min.js
doc/_templates/download.html
doc/_templates/layout.html
doc/_templates/page.html
doc/_templates/projects.html
doc/images/opbasm_logo.png
doc/images/opbasm_perf.png
doc/images/pb_update.png
doc/images/pb_update.svg
doc/images/static_analysis.png
doc/images/static_analysis.svg
doc/rst/m4.rst
doc/rst/opbsim.rst
doc/util/PicoBlazeLexer.py
doc/util/PicoBlazeLexer.pyc
example/deep_thought.psm4
example/vsim/README.txt
example/vsim/example.psm4
example/vsim/example.vhdl
example/vsim/example_wave.do
example/vsim/sizing.vhdl
example/vsim/timing_ops.vhdl
opbasm.egg-info/PKG-INFO
opbasm.egg-info/SOURCES.txt
opbasm.egg-info/dependency_links.txt
opbasm.egg-info/entry_points.txt
opbasm.egg-info/top_level.txt
opbasm_lib/__init__.py
opbasm_lib/color.py
opbasm_lib/hamming.py
opbasm_lib/picoblaze.m4
opbasm_lib/win_console.py
opbasm_lib/lang/opbasm.pot
opbasm_lib/lang/pb_update.pot
opbasm_lib/lang/de/LC_MESSAGES/opbasm.mo
opbasm_lib/lang/de/LC_MESSAGES/opbasm.po
opbasm_lib/lang/de/LC_MESSAGES/pb_update.mo
opbasm_lib/lang/de/LC_MESSAGES/pb_update.po
opbasm_lib/lang/fr/LC_MESSAGES/opbasm.mo
opbasm_lib/lang/fr/LC_MESSAGES/opbasm.po
opbasm_lib/lang/fr/LC_MESSAGES/pb_update.mo
opbasm_lib/lang/fr/LC_MESSAGES/pb_update.po
opbasm_lib/m4/COPYING
opbasm_lib/m4/README.txt
opbasm_lib/m4/m4-1.4.14-1-GnuWin32.README
opbasm_lib/m4/m4.exe
opbasm_lib/m4/regex-2.7-GnuWin32.README
opbasm_lib/m4/regex2.dll
sim/engineering.nim
sim/opbsim.nim
sim/opbsim.nimble
sim/win64/LICENCE
sim/win64/pcre.dll
templates/ROM_form_S3_1K.vhdl
templates/picoblaze_rom.vhdl
test/__init__.py
test/psm_gen.py
test/test_auto.py
test/test_opbasm.py
test/asm/ansi.psm4
test/asm/arithmetic.psm4
test/asm/bcd.psm4
test/asm/bitfields.psm4
test/asm/carry_flag.psm4
test/asm/conditionals.psm4
test/asm/control_structs.psm4
test/asm/delays.psm4
test/asm/functions.psm4
