Metadata-Version: 1.1
Name: opbasm
Version: 1.3
Summary: Open Picoblaze Assembler
Home-page: http://code.google.com/p/opbasm/
Author: Kevin Thibedeau
Author-email: kevin.thibedeau@gmail.com
License: MIT
Download-URL: http://code.google.com/p/opbasm/
Keywords: Picoblaze assembler
Platform: Any
Classifier: Development Status :: 5 - Production/Stable
Classifier: Operating System :: OS Independent
Classifier: Intended Audience :: Developers
Classifier: Topic :: Software Development :: Assemblers
Classifier: Topic :: Software Development :: Embedded Systems
Classifier: Natural Language :: English
Classifier: Programming Language :: Python :: 2.7
Classifier: Programming Language :: Python :: 3
Classifier: Programming Language :: Assembly
Classifier: License :: OSI Approved :: MIT License
